leafhopper/__init__.py
leafhopper/descriptors/__init__.py
leafhopper/descriptors/descriptor.py
leafhopper/descriptors/extra/__init__.py
leafhopper/descriptors/extra/extra_info_loader.py
leafhopper/descriptors/extra/github_info_loader.py
leafhopper/descriptors/extra/sourceforge_info_loader.py
leafhopper/descriptors/mvn.py
leafhopper/descriptors/poetry.py
leafhopper/descriptors/vcpkg.py
leafhopper/extra_pkgs.py
leafhopper/logger.py
leafhopper/main.py
leafhopper/pkg_table_writer.py
leafhopper-0.4.0.dist-info/entry_points.txt
leafhopper-0.4.0.dist-info/LICENSE
leafhopper-0.4.0.dist-info/WHEEL
leafhopper-0.4.0.dist-info/METADATA
leafhopper-0.4.0.dist-info/RECORD
